[{
    "title": "Rep",
    "firstname": "Alex",
    "middlename": "",
    "lastname": "Mooney",
    "name_suffix": "",
    "nickname": "",
    "party": "R",
    "state": "WV",
    "district": "2",
    "in_office": "1",
    "gender": "M",
    "phone": "202-225-2711",
    "fax": "202-225-7856",
    "website": "https://mooney.house.gov",
    "webform": "",
    "congress_office": "1232 Longworth House Office Building",
    "bioguide_id": "M001195",
    "votesmart_id": "",
    "fec_id": "H4WV02080",
    "govtrack_id": "412662",
    "crp_id": "N00033814",
    "twitter_id": "RepAlexMooney",
    "congresspedia_url": "",
    "youtube_url": "",
    "facebook_id": "CongressmanAlexMooney",
    "official_rss": "",
    "senate_class": "",
    "birthdate": "1971-06-05",
    "oc_email": "Rep.Mooney@opencongress.org"
}, {
    "title": "Sen",
    "firstname": "Shelley",
    "middlename": "Moore",
    "lastname": "Capito",
    "name_suffix": "",
    "nickname": "",
    "party": "R",
    "state": "WV",
    "district": "Junior Seat",
    "in_office": "1",
    "gender": "F",
    "phone": "202-224-6472",
    "fax": "",
    "website": "https://www.capito.senate.gov",
    "webform": "",
    "congress_office": "172 Russell Senate Office Building",
    "bioguide_id": "C001047",
    "votesmart_id": "11701",
    "fec_id": "H0WV02138",
    "govtrack_id": "400061",
    "crp_id": "N00009771",
    "twitter_id": "SenCapito",
    "congresspedia_url": "http://www.opencongress.org/wiki/Shelley_Moore_Capito",
    "youtube_url": "http://youtube.com/UCbiXdR4XQ3vD9Xp5lfR9QXw",
    "facebook_id": "8057864757",
    "official_rss": "",
    "senate_class": "II",
    "birthdate": "1953-11-26",
    "oc_email": "Sen.Capito@opencongress.org"
}, {
    "title": "Sen",
    "firstname": "Joe",
    "middlename": "",
    "lastname": "Manchin",
    "name_suffix": "III",
    "nickname": "",
    "party": "D",
    "state": "WV",
    "district": "Senior Seat",
    "in_office": "1",
    "gender": "M",
    "phone": "202-224-3954",
    "fax": "202-228-0002",
    "website": "http://www.manchin.senate.gov",
    "webform": "http://www.manchin.senate.gov/public/index.cfm/contact-form",
    "congress_office": "306 Hart Senate Office Building",
    "bioguide_id": "M001183",
    "votesmart_id": "7547",
    "fec_id": "S0WV00090",
    "govtrack_id": "412391",
    "crp_id": "N00032838",
    "twitter_id": "Sen_JoeManchin",
    "congresspedia_url": "http://www.opencongress.org/wiki/Joe_Manchin",
    "youtube_url": "http://youtube.com/SenatorJoeManchin",
    "facebook_id": "10150135395755161",
    "official_rss": "",
    "senate_class": "I",
    "birthdate": "1947-08-24",
    "oc_email": "Sen.Manchin@opencongress.org"
}]